LICENSE
MANIFEST.in
README.rst
setup.py
scheduleduty/__init__.py
scheduleduty/scheduleduty.py
scheduleduty.egg-info/PKG-INFO
scheduleduty.egg-info/SOURCES.txt
scheduleduty.egg-info/dependency_links.txt
scheduleduty.egg-info/requires.txt
scheduleduty.egg-info/top_level.txt