Metadata-Version: 1.0
Name: scheduleduty
Version: 0.2.3
Summary: Tool to import schedules saved as CSV files into PagerDuty
Home-page: https://github.com/lfepp/scheduleduty
Author: Lucas Epp
Author-email: lucas@pagerduty.com
License: Copyright (c) 2016, PagerDuty, Inc. <info@pagerduty.com>
